spacy_pythainlp/ __init__.py
spacy_pythainlp/core.py
spacy_pythainlp-0.1.dist-info/LICENSE
spacy_pythainlp-0.1.dist-info/METADATA
spacy_pythainlp-0.1.dist-info/WHEEL
spacy_pythainlp-0.1.dist-info/top_level.txt
spacy_pythainlp-0.1.dist-info/RECORD
