Metadata-Version: 2.1
Name: spacy-pythainlp
Version: 0.1
Summary: PyThaiNLP For spaCy
Home-page: https://github.com/PyThaiNLP/spaCy-PyThaiNLP
Author: Wannaphong Phatthiyaphaibun
Author-email: wannaphong@yahoo.com
License: Apache Software License 2.0
Project-URL: Source Code, https://github.com/PyThaiNLP/spaCy-PyThaiNLP
Project-URL: Bug Tracker, https://github.com/PyThaiNLP/spaCy-PyThaiNLP/issues
Keywords: pythainlp,NLP,natural language processing,text analytics,text processing,localization,computational linguistics,ThaiNLP,Thai NLP,Thai language
Classifier: Programming Language :: Python :: 3
Classifier: Intended Audience :: Developers
Classifier: License :: OSI Approved :: Apache Software License
Classifier: Natural Language :: Thai
Classifier: Topic :: Scientific/Engineering :: Artificial Intelligence
Classifier: Topic :: Text Processing
Classifier: Topic :: Text Processing :: General
Classifier: Topic :: Text Processing :: Linguistic
Requires-Python: >=3.7
License-File: LICENSE
Requires-Dist: pythainlp (>=3.1.0)
Requires-Dist: spacy (>=3.0)
Requires-Dist: gensim (>=4.0)
Requires-Dist: python-crfsuite
